python_dsalgo/__init__.py
python_dsalgo/data_structure/__init__.py
python_dsalgo/data_structure/binary_search_tree.py
python_dsalgo/data_structure/circular_doubly_linked_list.py
python_dsalgo/data_structure/circular_singly_linked_list.py
python_dsalgo/data_structure/doubly_linked_list.py
python_dsalgo/data_structure/graph_AL.py
python_dsalgo/data_structure/graph_AM.py
python_dsalgo/data_structure/hash_table.py
python_dsalgo/data_structure/max_heap.py
python_dsalgo/data_structure/min_heap.py
python_dsalgo/data_structure/queue.py
python_dsalgo/data_structure/singly_linked_list.py
python_dsalgo/data_structure/stack.py
python_dsalgo/searching/__init__.py
python_dsalgo/searching/bfs.py
python_dsalgo/searching/binary_search.py
python_dsalgo/searching/dfs.py
python_dsalgo/searching/linear_search.py
python_dsalgo/sorting/__init__.py
python_dsalgo/sorting/bubble_sort.py
python_dsalgo/sorting/bucket_sort.py
python_dsalgo/sorting/counting_sort.py
python_dsalgo/sorting/heap_sort.py
python_dsalgo/sorting/insertion_sort.py
python_dsalgo/sorting/merge_sort.py
python_dsalgo/sorting/quick_sort.py
python_dsalgo/sorting/radix_sort.py
python_dsalgo/sorting/selection_sort.py
python_dsalgo/sorting/shell_sort.py
python_dsalgo-0.1.0.dist-info/LICENSE.md
python_dsalgo-0.1.0.dist-info/METADATA
python_dsalgo-0.1.0.dist-info/WHEEL
python_dsalgo-0.1.0.dist-info/top_level.txt
python_dsalgo-0.1.0.dist-info/RECORD
